{
  "schema_version": "1.0",
  "namespace": "intel.com",
  "type": "reference",
  "status": "draft",
  "status_notes": "Generated from glossary research sweep 2026-05-21; org metadata copied from existing same-org entries under other SecID types.",
  "official_name": "Intel Corporation",
  "common_name": null,
  "alternate_names": null,
  "notes": "CVE Program partner. Country: USA.",
  "wikidata": null,
  "wikipedia": null,
  "urls": [
    {
      "type": "website",
      "url": "https://intel.com"
    }
  ],
  "match_nodes": [
    {
      "patterns": [
        "(?i)^software-security-glossary$"
      ],
      "description": "Intel Software Security Guidance Glossary",
      "weight": 100,
      "data": {
        "official_name": "Intel Software Security Guidance Glossary",
        "common_name": null,
        "alternate_names": null,
        "description": "Intel Software Security Guidance Glossary",
        "notes": "",
        "urls": [
          {
            "type": "source",
            "url": "https://www.intel.com/content/www/us/en/developer/articles/technical/software-security-guidance/glossary.html"
          }
        ],
        "examples": []
      }
    }
  ]
}