{
  "schema_version": "1.0",
  "namespace": "ul.org",
  "type": "entity",
  "status": "draft",
  "status_notes": null,
  "official_name": "UL Standards & Engagement",
  "common_name": "UL",
  "alternate_names": [
    "Underwriters Laboratories"
  ],
  "notes": "US-based safety-science and standards organization. Publishes the UL 2900-series cybersecurity-for-products standards (UL 2900-1 general; UL 2900-2-1 healthcare; UL 2900-2-2 industrial control; UL 2900-2-3 life-safety signaling). Paid.",
  "wikidata": null,
  "wikipedia": null,
  "urls": [
    {
      "type": "website",
      "url": "https://www.ul.org"
    }
  ],
  "match_nodes": []
}
