{
  "schema_version": "1.0",
  "namespace": "eei.org",
  "type": "control",
  "status": "draft",
  "status_notes": null,
  "official_name": "Edison Electric Institute",
  "common_name": "EEI",
  "alternate_names": null,
  "notes": "US investor-owned electric-utility trade association. Publishes operational guidance and procurement language including EEI Model Procurement Contract Language for Cybersecurity Supply Chain. Members-only.",
  "wikidata": null,
  "wikipedia": null,
  "urls": [
    {
      "type": "website",
      "url": "https://www.eei.org"
    }
  ],
  "match_nodes": [
    {
      "patterns": [
        "(?i)^model-procurement-cyber$"
      ],
      "description": "EEI Model Procurement Contract Language for Cybersecurity Supply Chain",
      "weight": 100,
      "data": {
        "official_name": "EEI Model Procurement Contract Language for Cybersecurity Supply Chain",
        "notes": "Members-only. Standard contract clauses for cyber supply-chain in utility procurement.",
        "urls": [
          {
            "type": "website",
            "url": "https://www.eei.org"
          }
        ],
        "versions_available": [],
        "examples": []
      }
    }
  ]
}
