{
  "schema_version": "1.0",
  "namespace": "bd.com",
  "type": "disclosure",
  "status": "draft",
  "status_notes": "Generated from CVE CNA partner data (cve.org), 2026-04-03.",
  "official_name": "Becton, Dickinson and Company (BD)",
  "common_name": null,
  "alternate_names": null,
  "notes": "CVE Program partner. Country: USA.",
  "wikidata": null,
  "wikipedia": null,
  "urls": [
    {
      "type": "website",
      "url": "https://bd.com"
    }
  ],
  "match_nodes": [
    {
      "patterns": [
        "(?i)^cna$"
      ],
      "description": "CNA",
      "weight": 80,
      "data": {
        "scope": "BD software-enabled medical devices only.",
        "cve_program_role": "CNA",
        "organization_type": "Vendor",
        "contacts": [
          {
            "type": "email",
            "value": "SMB-BD-CNA@bd.com",
            "note": "Email"
          }
        ],
        "urls": [
          {
            "type": "docs",
            "url": "https://cybersecurity.bd.com/vulnerability-disclosures",
            "note": "Disclosure policy"
          },
          {
            "type": "website",
            "url": "https://cybersecurity.bd.com/bulletins-and-patches",
            "note": "Security advisories"
          },
          {
            "type": "website",
            "url": "https://www.cve.org/PartnerInformation/ListofPartners/partner/BD",
            "note": "CVE partner page"
          }
        ],
        "examples": []
      }
    }
  ]
}