{
  "schema_version": "1.0",
  "namespace": "octopus.com",
  "type": "disclosure",
  "status": "draft",
  "status_notes": "Generated from CVE CNA partner data (cve.org), 2026-04-03.",
  "official_name": "Octopus Deploy",
  "common_name": null,
  "alternate_names": null,
  "notes": "CVE Program partner. Country: Australia.",
  "wikidata": null,
  "wikipedia": null,
  "urls": [
    {
      "type": "website",
      "url": "https://octopus.com"
    }
  ],
  "match_nodes": [
    {
      "patterns": [
        "(?i)^cna$"
      ],
      "description": "CNA",
      "weight": 80,
      "data": {
        "scope": "All Octopus Deploy products, as well as Octopus Deploy maintained projects hosted on https://github.com/OctopusDeploy.",
        "cve_program_role": "CNA",
        "organization_type": "Vendor, Open Source",
        "contacts": [
          {
            "type": "email",
            "value": "security@octopus.com",
            "note": "Email"
          }
        ],
        "urls": [
          {
            "type": "docs",
            "url": "https://octopus.com/security/disclosure",
            "note": "Disclosure policy"
          },
          {
            "type": "website",
            "url": "https://advisories.octopus.com/",
            "note": "Security advisories"
          },
          {
            "type": "website",
            "url": "https://www.cve.org/PartnerInformation/ListofPartners/partner/Octopus",
            "note": "CVE partner page"
          }
        ],
        "examples": []
      }
    }
  ]
}